setup.py
olacabs/__init__.py
olacabs/client.py
olacabs/exceptions.py
olacabs.egg-info/PKG-INFO
olacabs.egg-info/SOURCES.txt
olacabs.egg-info/dependency_links.txt
olacabs.egg-info/not-zip-safe
olacabs.egg-info/pbr.json
olacabs.egg-info/requires.txt
olacabs.egg-info/top_level.txt