Metadata-Version: 1.1
Name: olacabs
Version: 0.0.3
Summary: Python client for Olacabs APIs
Home-page: http://sandeepk.in
Author: Sandeep Kumar
Author-email: 4sandeep.kumar@gmail.com
License: UNKNOWN
Platform: UNKNOWN
Classifier: Environment :: Web Environment
Classifier: Intended Audience :: Developers
Classifier: License :: OSI Approved :: MIT License
Classifier: Operating System :: OS Independent
Classifier: Programming Language :: Python
Classifier: Programming Language :: Python :: 3
Classifier: Topic :: Internet :: WWW/HTTP
